langflow/__init__.py
langflow/__main__.py
langflow/alembic/README
langflow/alembic/env.py
langflow/alembic/script.py.mako
langflow/alembic/versions/006b3990db50_add_unique_constraints.py
langflow/alembic/versions/0b8757876a7c_.py
langflow/alembic/versions/1ef9c4f3765d_.py
langflow/alembic/versions/260dbcc8b680_adds_tables.py
langflow/alembic/versions/2ac71eb9c3ae_adds_credential_table.py
langflow/alembic/versions/67cc006d50bf_add_profile_image_column.py
langflow/alembic/versions/7843803a87b5_store_updates.py
langflow/alembic/versions/7d2162acc8b2_adds_updated_at_and_folder_cols.py
langflow/alembic/versions/b2fa308044b5_add_unique_constraints.py
langflow/alembic/versions/bc2f01c40e4a_new_fixes.py
langflow/alembic/versions/eb5866d51fd2_change_columns_to_be_nullable.py
langflow/alembic/versions/f5ee9749d1a6_user_id_can_be_null_in_flow.py
langflow/alembic/versions/fd531f8868b1_fix_credential_table.py
langflow/alembic.ini
langflow/api/__init__.py
langflow/api/router.py
langflow/api/utils.py
langflow/api/v1/__init__.py
langflow/api/v1/api_key.py
langflow/api/v1/base.py
langflow/api/v1/callback.py
langflow/api/v1/chat.py
langflow/api/v1/credential.py
langflow/api/v1/endpoints.py
langflow/api/v1/flows.py
langflow/api/v1/login.py
langflow/api/v1/schemas.py
langflow/api/v1/store.py
langflow/api/v1/users.py
langflow/api/v1/validate.py
langflow/components/__init__.py
langflow/components/agents/AgentInitializer.py
langflow/components/agents/CSVAgent.py
langflow/components/agents/JsonAgent.py
langflow/components/agents/OpenAIConversationalAgent.py
langflow/components/agents/SQLAgent.py
langflow/components/agents/VectorStoreAgent.py
langflow/components/agents/VectorStoreRouterAgent.py
langflow/components/agents/__init__.py
langflow/components/chains/ConversationChain.py
langflow/components/chains/LLMChain.py
langflow/components/chains/LLMCheckerChain.py
langflow/components/chains/LLMMathChain.py
langflow/components/chains/PromptRunner.py
langflow/components/chains/RetrievalQA.py
vesslflow-0.6.13.dist-info/LICENSE
vesslflow-0.6.13.dist-info/METADATA
vesslflow-0.6.13.dist-info/WHEEL
vesslflow-0.6.13.dist-info/entry_points.txt
vesslflow-0.6.13.dist-info/RECORD
