Metadata-Version: 2.1
Name: vesslflow
Version: 0.6.13
Summary: VESSLFlow
License: MIT
Keywords: nlp,openai,gpt,gui
Author: Lucas VESSL
Requires-Python: >=3.9,<3.12
Classifier: License :: OSI Approved :: MIT License
Classifier: Programming Language :: Python :: 3
Classifier: Programming Language :: Python :: 3.9
Classifier: Programming Language :: Python :: 3.10
Classifier: Programming Language :: Python :: 3.11
Provides-Extra: all
Provides-Extra: deploy
Provides-Extra: local
Requires-Dist: alembic (>=1.13.0,<2.0.0)
Requires-Dist: bcrypt (==4.0.1)
Requires-Dist: beautifulsoup4 (>=4.12.2,<5.0.0)
Requires-Dist: boto3 (>=1.34.0,<2.0.0)
Requires-Dist: cachetools (>=5.3.1,<6.0.0)
Requires-Dist: celery[redis] (>=5.3.6,<6.0.0) ; extra == "deploy"
Requires-Dist: certifi (>=2023.11.17,<2024.0.0)
Requires-Dist: chromadb (>=0.4.0,<0.5.0)
Requires-Dist: cohere (>=4.47.0,<5.0.0)
Requires-Dist: ctransformers (>=0.2.10,<0.3.0) ; extra == "local"
Requires-Dist: docstring-parser (>=0.15,<0.16)
Requires-Dist: elasticsearch (>=8.12.0,<9.0.0)
Requires-Dist: extract-msg (>=0.47.0,<0.48.0)
Requires-Dist: faiss-cpu (>=1.7.4,<2.0.0)
Requires-Dist: fake-useragent (>=1.4.0,<2.0.0)
Requires-Dist: fastapi (>=0.109.0,<0.110.0)
Requires-Dist: fastavro (>=1.8.0,<2.0.0)
Requires-Dist: flower (>=2.0.0,<3.0.0) ; extra == "deploy"
Requires-Dist: google-api-python-client (>=2.118.0,<3.0.0)
Requires-Dist: google-cloud-aiplatform (>=1.42.0,<2.0.0)
Requires-Dist: google-search-results (>=2.4.1,<3.0.0)
Requires-Dist: gunicorn (>=21.2.0,<22.0.0)
Requires-Dist: huggingface-hub[inference] (>=0.20.0,<0.21.0)
Requires-Dist: jq (>=1.6.0,<2.0.0) ; sys_platform != "win32"
Requires-Dist: langchain (>=0.1.0,<0.2.0)
Requires-Dist: langchain-anthropic (>=0.1.4,<0.2.0)
Requires-Dist: langchain-experimental
Requires-Dist: langchain-google-genai (>=0.0.6,<0.0.7)
Requires-Dist: langchain-openai (>=0.0.6,<0.0.7)
Requires-Dist: langfuse (>=2.9.0,<3.0.0)
Requires-Dist: llama-cpp-python (>=0.2.0,<0.3.0) ; extra == "local"
Requires-Dist: llama-index (==0.9.48)
Requires-Dist: loguru (>=0.7.1,<0.8.0)
Requires-Dist: lxml (>=4.9.2,<5.0.0)
Requires-Dist: markupsafe (>=2.1.3,<3.0.0)
Requires-Dist: metal-sdk (>=2.5.0,<3.0.0)
Requires-Dist: metaphor-python (>=0.1.11,<0.2.0)
Requires-Dist: multiprocess (>=0.70.14,<0.71.0)
Requires-Dist: networkx (>=3.1,<4.0)
Requires-Dist: numexpr (>=2.8.6,<3.0.0)
Requires-Dist: openai (>=1.12.0,<2.0.0)
Requires-Dist: orjson (==3.9.15)
Requires-Dist: pandas (==2.2.0)
Requires-Dist: passlib (>=1.7.4,<2.0.0)
Requires-Dist: pgvector (>=0.2.3,<0.3.0)
Requires-Dist: pillow (>=10.2.0,<11.0.0)
Requires-Dist: pinecone-client (>=3.0.3,<4.0.0)
Requires-Dist: platformdirs (>=4.2.0,<5.0.0)
Requires-Dist: psycopg (>=3.1.9,<4.0.0)
Requires-Dist: psycopg-binary (>=3.1.9,<4.0.0)
Requires-Dist: psycopg2-binary (>=2.9.6,<3.0.0)
Requires-Dist: pyarrow (>=14.0.0,<15.0.0)
Requires-Dist: pyautogen (>=0.2.0,<0.3.0)
Requires-Dist: pydantic (>=2.6.0,<3.0.0)
Requires-Dist: pydantic-settings (>=2.1.0,<3.0.0)
Requires-Dist: pymongo (>=4.6.0,<5.0.0)
Requires-Dist: pypdf (>=4.0.0,<5.0.0)
Requires-Dist: pysrt (>=1.1.2,<2.0.0)
Requires-Dist: python-jose (>=3.3.0,<4.0.0)
Requires-Dist: python-multipart (>=0.0.7,<0.0.8)
Requires-Dist: pytube (>=15.0.0,<16.0.0)
Requires-Dist: pywin32 (>=306,<307) ; sys_platform == "win32"
Requires-Dist: qdrant-client (>=1.7.0,<2.0.0)
Requires-Dist: qianfan (==0.3.0)
Requires-Dist: redis (>=5.0.1,<6.0.0) ; extra == "deploy"
Requires-Dist: rich (>=13.7.0,<14.0.0)
Requires-Dist: sentence-transformers (>=2.3.1,<3.0.0) ; extra == "local"
Requires-Dist: sqlmodel (>=0.0.14,<0.0.15)
Requires-Dist: supabase (>=2.3.0,<3.0.0)
Requires-Dist: tiktoken (>=0.6.0,<0.7.0)
Requires-Dist: typer (>=0.9.0,<0.10.0)
Requires-Dist: types-cachetools (>=5.3.0.5,<6.0.0.0)
Requires-Dist: unstructured (>=0.12.0,<0.13.0)
Requires-Dist: urllib3 (<2)
Requires-Dist: uvicorn (>=0.27.0,<0.28.0)
Requires-Dist: weaviate-client
Requires-Dist: websockets (>=10.3,<11.0)
Requires-Dist: wikipedia (>=1.4.0,<2.0.0)
Requires-Dist: zep-python
